cololog/__init__.py
cololog/cololog.py
cololog-0.1.0.dist-info/LICENSE
cololog-0.1.0.dist-info/METADATA
cololog-0.1.0.dist-info/WHEEL
cololog-0.1.0.dist-info/top_level.txt
cololog-0.1.0.dist-info/RECORD
