Metadata-Version: 2.1
Name: cololog
Version: 0.1.0
Summary: Цветной регистратор с настраиваемыми уровнями и выводом в файл.
Home-page: https://github.com/AsQqqq/cololog
Author: AsQ
Author-email: asqdanil@yandex.ru
Classifier: Programming Language :: Python :: 3
Classifier: License :: OSI Approved :: MIT License
Classifier: Operating System :: OS Independent
Requires-Python: >=3.6
License-File: LICENSE
Requires-Dist: colorama
